cocmd_cli/.gitignore
cocmd_cli/__init__.py
cocmd_cli/__main__.py
cocmd_cli/commands/__init__.py
cocmd_cli/commands/groups.py
cocmd_cli/commands/run.py
cocmd_cli/commands/stubs.py
cocmd_cli/commands/subcommands/add.py
cocmd_cli/commands/subcommands/remove.py
cocmd_cli/commands/subcommands/show.py
cocmd_cli/consts.py
cocmd_cli/core/aliases.py
cocmd_cli/core/models/creds_config_model.py
cocmd_cli/core/models/script_model.py
cocmd_cli/core/models/source_config_model.py
cocmd_cli/core/os.py
cocmd_cli/core/script_runner.py
cocmd_cli/core/source.py
cocmd_cli/core/sources_manager.py
cocmd_cli/resources/__init__.py
cocmd_cli/resources/demo/aws-s3/cocmd.yaml
cocmd_cli/resources/demo/docker/cocmd.buildrun.yaml
cocmd_cli/resources/demo/docker/cocmd.clean.yaml
cocmd_cli/resources/demo/docker/cocmd.monitor.yaml
cocmd_cli/resources/demo/docker/cocmd.setup.debian.yaml
cocmd_cli/resources/demo/docker/cocmd.setup.osx.yaml
cocmd_cli/resources/demo/docker/cocmd.yaml
cocmd_cli/resources/demo/git/aliases.txt
cocmd_cli/resources/demo/git/cocmd.yaml
cocmd_cli/resources/demo/k8s/aliases.txt
cocmd_cli/resources/demo/k8s/cocmd.yaml
cocmd_cli/resources/demo/k8s/scripts/setup.yaml
cocmd_cli/resources/demo/osx/aliases.txt
cocmd_cli/resources/demo/osx/ggist.yaml
cocmd_cli/resources/demo/osx/scripts/devmachine.yaml
cocmd_cli/resources/demo/team1/aliases.txt
cocmd_cli/resources/demo/team1/ggist.yaml
cocmd_cli/resources/demo/team1/scripts/onboarding.yaml
cocmd_cli/resources/demo/zsh/aliases.txt
cocmd_cli/resources/demo/zsh/ggist.yaml
cocmd_cli/resources/demo/zsh/scripts/setup.yaml
cocmd_cli/settings.py
cocmd_cli/utils/console.py
cocmd_cli/utils/git.py
cocmd_cli/utils/io.py
cocmd_cli/utils/repository.py
cocmd_cli/utils/sys.py
cocmd-0.1.1.dist-info/LICENSE
cocmd-0.1.1.dist-info/METADATA
cocmd-0.1.1.dist-info/WHEEL
cocmd-0.1.1.dist-info/entry_points.txt
cocmd-0.1.1.dist-info/RECORD
